ogmaneo/__init__.py
ogmaneo/core.cl
ogmaneo/decoder.py
ogmaneo/encoder.py
ogmaneo/extra.cl
ogmaneo/helpers.py
ogmaneo/hierarchy.py
ogmaneo/imageenc.py
clogmaneo-1.2.0.dist-info/LICENSE.md
clogmaneo-1.2.0.dist-info/METADATA
clogmaneo-1.2.0.dist-info/WHEEL
clogmaneo-1.2.0.dist-info/top_level.txt
clogmaneo-1.2.0.dist-info/RECORD
