Metadata-Version: 2.1
Name: clogmaneo
Version: 1.2.0
Summary: PyOpenCL implementation of Sparse Predictive Hierarchies
Author-email: Eric Laukien <eric@ogmacorp.com>
License: Creative Commons Attribution-NonCommercial-ShareAlike 4.0 International
Project-URL: Homepage, https://github.com/ogmacorp/CLOgmaNeo
Keywords: sph,ai,ml
Classifier: License :: Free for non-commercial use
Classifier: Programming Language :: Python
Classifier: Programming Language :: Python :: 3
Requires-Python: >=3.9
License-File: LICENSE.md
Requires-Dist: pyopencl
